{
  "run_id": "endurance-1773844767",
  "status": "Archived",
  "task": "Urgent: Deploy feature with tight deadline but incomplete testing. Risk assessment required.",
  "input_type": "conflict",
  "worktree_path": "./runtime_state/worktrees/endurance-1773844767",
  "tmux_session": "dragoncore_endurance-1773844767",
  "created_at": "2026-03-18T14:39:27.620549728Z",
  "updated_at": "2026-03-18T14:44:02.880841522Z",
  "events": [
    {
      "timestamp": "2026-03-18T14:44:02.821129090Z",
      "seat": "Tianshu",
      "action": "final_gate",
      "details": "approved: true"
    },
    {
      "timestamp": "2026-03-18T14:44:02.880840961Z",
      "seat": "Yaoguang",
      "action": "archive",
      "details": null
    }
  ],
  "metrics": {
    "seat_participation": {},
    "veto_count": 0,
    "revision_count": 0
  },
  "veto": null,
  "final_gate": {
    "seat": "Tianshu",
    "approved": true,
    "timestamp": "2026-03-18T14:44:02.821128398Z"
  },
  "current_seat": null,
  "seats_participated": [],
  "artifacts": []
}